dfnbutils/__init__.py
dfnbutils/refs.py
dfnbutils-1.0.0b1.dist-info/METADATA
dfnbutils-1.0.0b1.dist-info/WHEEL
dfnbutils-1.0.0b1.dist-info/top_level.txt
dfnbutils-1.0.0b1.dist-info/RECORD
